sapiens_accelerator/__init__.py
sapiens_accelerator/accelerator.py
sapiens_accelerator/big_modeling.py
sapiens_accelerator/checkpointing.py
sapiens_accelerator/data_loader.py
sapiens_accelerator/hooks.py
sapiens_accelerator/inference.py
sapiens_accelerator/launchers.py
sapiens_accelerator/local_sgd.py
sapiens_accelerator/logging.py
sapiens_accelerator/memory_utils.py
sapiens_accelerator/optimizer.py
sapiens_accelerator/scheduler.py
sapiens_accelerator/state.py
sapiens_accelerator/tracking.py
sapiens_accelerator/commands/__init__.py
sapiens_accelerator/commands/accelerate_cli.py
sapiens_accelerator/commands/env.py
sapiens_accelerator/commands/estimate.py
sapiens_accelerator/commands/launch.py
sapiens_accelerator/commands/merge.py
sapiens_accelerator/commands/test.py
sapiens_accelerator/commands/tpu.py
sapiens_accelerator/commands/utils.py
sapiens_accelerator/commands/config/__init__.py
sapiens_accelerator/commands/config/cluster.py
sapiens_accelerator/commands/config/config.py
sapiens_accelerator/commands/config/config_args.py
sapiens_accelerator/commands/config/config_utils.py
sapiens_accelerator/commands/config/default.py
sapiens_accelerator/commands/config/sagemaker.py
sapiens_accelerator/commands/config/update.py
sapiens_accelerator/commands/menu/__init__.py
sapiens_accelerator/commands/menu/cursor.py
sapiens_accelerator/commands/menu/helpers.py
sapiens_accelerator/commands/menu/input.py
sapiens_accelerator/commands/menu/keymap.py
sapiens_accelerator/commands/menu/selection_menu.py
sapiens_accelerator/test_utils/__init__.py
sapiens_accelerator/test_utils/examples.py
sapiens_accelerator/test_utils/testing.py
sapiens_accelerator/test_utils/training.py
sapiens_accelerator/test_utils/scripts/__init__.py
sapiens_accelerator/test_utils/scripts/test_cli.py
sapiens_accelerator/test_utils/scripts/test_ddp_comm_hook.py
sapiens_accelerator/test_utils/scripts/test_distributed_data_loop.py
sapiens_accelerator/test_utils/scripts/test_merge_weights.py
sapiens_accelerator-1.0.7.dist-info/LICENSE.txt
sapiens_accelerator-1.0.7.dist-info/METADATA
sapiens_accelerator-1.0.7.dist-info/WHEEL
sapiens_accelerator-1.0.7.dist-info/entry_points.txt
sapiens_accelerator-1.0.7.dist-info/top_level.txt
sapiens_accelerator-1.0.7.dist-info/RECORD
