Metadata-Version: 2.2
Name: sapiens_accelerator
Version: 1.0.7
Home-page: https://github.com/sapiens-technology/sapiens_accelerator
Author: OPENSAPI
License: Proprietary Software
Requires-Python: >=3.9.0
License-File: LICENSE.txt
Requires-Dist: numpy
Requires-Dist: packaging
Requires-Dist: psutil
Requires-Dist: PyYAML
Requires-Dist: torch
Requires-Dist: huggingface-hub
Requires-Dist: safetensors
Provides-Extra: quality
Requires-Dist: black~=23.1; extra == "quality"
Requires-Dist: hf-doc-builder==0.5.0; extra == "quality"
Requires-Dist: ruff~=0.6.4; extra == "quality"
Provides-Extra: docs
Provides-Extra: test-prod
Requires-Dist: pytest<=8.0.0,>=7.2.0; extra == "test-prod"
Requires-Dist: pytest-xdist==3.6.1; extra == "test-prod"
Requires-Dist: pytest-subtests==0.14.1; extra == "test-prod"
Requires-Dist: parameterized==0.9.0; extra == "test-prod"
Provides-Extra: test-dev
Requires-Dist: datasets==3.0.1; extra == "test-dev"
Requires-Dist: diffusers==0.32.2; extra == "test-dev"
Requires-Dist: evaluate==0.4.3; extra == "test-dev"
Requires-Dist: torchdata==0.10.1; extra == "test-dev"
Requires-Dist: torchpippy==0.2.0; extra == "test-dev"
Requires-Dist: transformers==4.45.2; extra == "test-dev"
Requires-Dist: scipy==1.15.1; extra == "test-dev"
Requires-Dist: scikit-learn==1.5.0; extra == "test-dev"
Requires-Dist: tqdm==4.66.4; extra == "test-dev"
Requires-Dist: sapiens-machine==1.0.9; extra == "test-dev"
Requires-Dist: timm==1.0.14; extra == "test-dev"
Provides-Extra: testing
Requires-Dist: pytest<=8.0.0,>=7.2.0; extra == "testing"
Requires-Dist: pytest-xdist==3.6.1; extra == "testing"
Requires-Dist: pytest-subtests==0.14.1; extra == "testing"
Requires-Dist: parameterized==0.9.0; extra == "testing"
Requires-Dist: datasets==3.0.1; extra == "testing"
Requires-Dist: diffusers==0.32.2; extra == "testing"
Requires-Dist: evaluate==0.4.3; extra == "testing"
Requires-Dist: torchdata==0.10.1; extra == "testing"
Requires-Dist: torchpippy==0.2.0; extra == "testing"
Requires-Dist: transformers==4.45.2; extra == "testing"
Requires-Dist: scipy==1.15.1; extra == "testing"
Requires-Dist: scikit-learn==1.5.0; extra == "testing"
Requires-Dist: tqdm==4.66.4; extra == "testing"
Requires-Dist: sapiens-machine==1.0.9; extra == "testing"
Requires-Dist: timm==1.0.14; extra == "testing"
Provides-Extra: deepspeed
Requires-Dist: deepspeed; extra == "deepspeed"
Provides-Extra: rich
Requires-Dist: rich; extra == "rich"
Provides-Extra: test-trackers
Requires-Dist: wandb==0.19.5; extra == "test-trackers"
Requires-Dist: comet-ml==3.48.1; extra == "test-trackers"
Requires-Dist: tensorboard==2.18.0; extra == "test-trackers"
Requires-Dist: dvclive==3.48.1; extra == "test-trackers"
Provides-Extra: dev
Requires-Dist: black~=23.1; extra == "dev"
Requires-Dist: hf-doc-builder==0.5.0; extra == "dev"
Requires-Dist: ruff~=0.6.4; extra == "dev"
Requires-Dist: pytest<=8.0.0,>=7.2.0; extra == "dev"
Requires-Dist: pytest-xdist==3.6.1; extra == "dev"
Requires-Dist: pytest-subtests==0.14.1; extra == "dev"
Requires-Dist: parameterized==0.9.0; extra == "dev"
Requires-Dist: datasets==3.0.1; extra == "dev"
Requires-Dist: diffusers==0.32.2; extra == "dev"
Requires-Dist: evaluate==0.4.3; extra == "dev"
Requires-Dist: torchdata==0.10.1; extra == "dev"
Requires-Dist: torchpippy==0.2.0; extra == "dev"
Requires-Dist: transformers==4.45.2; extra == "dev"
Requires-Dist: scipy==1.15.1; extra == "dev"
Requires-Dist: scikit-learn==1.5.0; extra == "dev"
Requires-Dist: tqdm==4.66.4; extra == "dev"
Requires-Dist: sapiens-machine==1.0.9; extra == "dev"
Requires-Dist: timm==1.0.14; extra == "dev"
Requires-Dist: rich; extra == "dev"
Provides-Extra: sagemaker
Requires-Dist: sagemaker==2.239.0; extra == "sagemaker"
Dynamic: author
Dynamic: home-page
Dynamic: license
Dynamic: provides-extra
Dynamic: requires-dist
Dynamic: requires-python
